libumi/__init__.py
libumi/hello_world.py
libumi/hello_world.pyi
libumi/py.typed
libumi-0.0.2.dist-info/LICENSE
libumi-0.0.2.dist-info/METADATA
libumi-0.0.2.dist-info/WHEEL
libumi-0.0.2.dist-info/top_level.txt
libumi-0.0.2.dist-info/RECORD
